tnm/config/__init__.py
tnm/config/_core.py
tnm/config/_loader.py
tnm/config/_typeguard.py
tnm/config/_utils.py
tnm/config/errors.py
tnm/config/loaders/__init__.py
tnm/config/loaders/_base.py
tnm/config/loaders/ini_loader.py
tnm/config/loaders/json_loader.py
tnm/config/loaders/toml_loader.py
tnm/config/loaders/xml_loader.py
tnm/config/loaders/yaml_loader.py
tnm_config-1.3.1.dist-info/licenses/LICENSE
tnm_config-1.3.1.dist-info/METADATA
tnm_config-1.3.1.dist-info/WHEEL
tnm_config-1.3.1.dist-info/top_level.txt
tnm_config-1.3.1.dist-info/RECORD
