Metadata-Version: 2.4
Name: tnm-config
Version: 1.3.1
Summary: Small config loader supporting YAML, JSON and XML with env support.
Author-email: Justice Sandram <justicesandram@gmail.com>
Project-URL: Repository, https://github.com/mpamba/tnm-config
Keywords: config,loader,yaml,json,xml,env,configuration
Classifier: Programming Language :: Python :: 3
Classifier: Programming Language :: Python :: 3.11
Classifier: Programming Language :: Python :: 3.12
Classifier: Programming Language :: Python :: 3.13
Classifier: Topic :: Internet :: WWW/HTTP
Requires-Python: >=3.11
License-File: LICENSE
Requires-Dist: typeguard>=4.0.1
Requires-Dist: python-dotenv>=1.0.0
Provides-Extra: yaml
Requires-Dist: PyYAML>=6.0; extra == "yaml"
Provides-Extra: xml
Requires-Dist: xmltodict>=0.13.0; extra == "xml"
Provides-Extra: all
Requires-Dist: PyYAML>=6.0; extra == "all"
Requires-Dist: xmltodict>=0.13.0; extra == "all"
Provides-Extra: dev
Requires-Dist: pytest>=7; extra == "dev"
Requires-Dist: pytest-cov; extra == "dev"
Requires-Dist: tox; extra == "dev"
Requires-Dist: ruff; extra == "dev"
Requires-Dist: black>=23; extra == "dev"
Requires-Dist: mypy>=1.9; extra == "dev"
Requires-Dist: twine; extra == "dev"
Requires-Dist: build; extra == "dev"
Requires-Dist: pydantic; extra == "dev"
Dynamic: license-file
